design_nest/__init__.py
design_nest/eplus_components/__init__.py
design_nest/eplus_components/airflow.py
design_nest/eplus_components/building.py
design_nest/eplus_components/climate.py
design_nest/eplus_components/construction.py
design_nest/eplus_components/helper.py
design_nest/eplus_components/internal_gains.py
design_nest/eplus_components/outputs.py
design_nest/eplus_components/schedules.py
design_nest/eplus_components/simulation_parameters.py
design_nest/eplus_components/systems.py
design_nest/eplus_components/zone.py
design_nest/eplus_components/zone_control.py
design_nest-0.1.0.dist-info/METADATA
design_nest-0.1.0.dist-info/RECORD
design_nest-0.1.0.dist-info/WHEEL
design_nest-0.1.0.dist-info/top_level.txt
generator/__init__.py
generator/generate.py
generator/generator.py
generator/settings.py
generator/utils.py
generator/templates/__init__.py
generator/templates/class.py
generator/templates/group.py
generator/templates/helper.py
generator/templates/model.py
